{
    "behavior": "", 
    "checkable": false, 
    "class": "a", 
    "clickable": true, 
    "content-desc": "", 
    "enabled": false, 
    "focusable": true, 
    "focused": false, 
    "hash": "ro9wPORkjNL78zS/G08oUw==\n", 
    "height": 50, 
    "hier_level": 0, 
    "human_hash": "a_X1206_Y1264_W104_H50", 
    "human_readable": "a_1206_1264_104_50_a_fffffffffffffffffffe1ffebf3fa432a93880308620a020a480ffffffff0000_1a4940225c37283c238042f625b48084", 
    "image_path": "ZDYwYjYzOGE1YWVhNzkzOTliZjIzYjE0ODk4YTgwODQ.png", 
    "index": -1, 
    "internal": {
        "elem_dict": {
            "attributes": {
                "href": "https://www.test.ai/"
            }, 
            "background-color": "rgba(0, 0, 0, 0)", 
            "class": "a", 
            "color": "rgb(43, 38, 197)", 
            "domLevel": 14, 
            "flags": {
                "checkable": false, 
                "clickable": true, 
                "enabled": false, 
                "focusable": true, 
                "focused": false, 
                "scrollable": false
            }, 
            "font-family": "ibm-plex-sans", 
            "font-weight": "400", 
            "fontSize": 17.6, 
            "height": 25, 
            "identifier": "", 
            "is-focused": false, 
            "is-hidden": false, 
            "name": "", 
            "tagName": "a", 
            "text": "Test.ai", 
            "type": "", 
            "value": "", 
            "width": 52, 
            "x": 603, 
            "xPercent": 31.627296587926505, 
            "y": 632, 
            "yPercent": 12.887280880554423
        }, 
        "location": {
            "x": 603, 
            "y": 632
        }, 
        "size": {
            "height": 25, 
            "width": 52
        }, 
        "tag_name": "a", 
        "text": "Test.ai"
    }, 
    "is_transformed": true, 
    "package": "", 
    "password": false, 
    "resource-id": "", 
    "screen_hash": "8f6ef1074a89847a2b63f0b16a9c616e", 
    "scrollable": false, 
    "tag_name": "a", 
    "text": "Test.ai", 
    "transformed": true, 
    "width": 104, 
    "x": 1206, 
    "y": 1264
}