{
    "behavior": "", 
    "checkable": false, 
    "class": "a", 
    "clickable": true, 
    "content-desc": "", 
    "enabled": false, 
    "focusable": true, 
    "focused": false, 
    "hash": "S5afk8oWFdpmNGn22jAguQ==\n", 
    "height": 50, 
    "hier_level": 0, 
    "human_hash": "a_X2656_Y1518_W122_H50", 
    "human_readable": "a_2656_1518_122_50_a_00000000000000000000e000a0819bff9f9b97b997f9ffff5bfd00000000ffff_b714deb09c1929d942d8ec24a646cc21", 
    "image_path": "ZGY0YmI0MTNkMDM4ZGMxZDE2NTc4ODBiMzcwYzkyNmQ.png", 
    "index": -1, 
    "internal": {
        "elem_dict": {
            "attributes": {
                "href": "/contact"
            }, 
            "background-color": "rgba(0, 0, 0, 0)", 
            "class": "a", 
            "color": "rgb(255, 255, 255)", 
            "domLevel": 15, 
            "flags": {
                "checkable": false, 
                "clickable": true, 
                "enabled": false, 
                "focusable": true, 
                "focused": false, 
                "scrollable": false
            }, 
            "font-family": "ibm-plex-sans", 
            "font-weight": "400", 
            "fontSize": 17.6, 
            "height": 25, 
            "identifier": "", 
            "is-focused": false, 
            "is-hidden": false, 
            "name": "", 
            "tagName": "a", 
            "text": "Contact", 
            "type": "", 
            "value": "", 
            "width": 61, 
            "x": 1328, 
            "xPercent": 69.71128608923884, 
            "y": 759, 
            "yPercent": 17.944549538898087
        }, 
        "location": {
            "x": 1328, 
            "y": 759
        }, 
        "size": {
            "height": 25, 
            "width": 61
        }, 
        "tag_name": "a", 
        "text": "Contact"
    }, 
    "is_transformed": true, 
    "package": "", 
    "password": false, 
    "resource-id": "", 
    "screen_hash": "60122df0d813e885341970961c30dd0e", 
    "scrollable": false, 
    "tag_name": "a", 
    "text": "Contact", 
    "transformed": true, 
    "width": 122, 
    "x": 2656, 
    "y": 1518
}